machine_learn/__init__.py
machine_learn/main.py
machine_learn/model/__init__.py
machine_learn/model/TSA.py
machine_learn/model_base.py
machine_learn-0.1.0.dist-info/entry_points.txt
machine_learn-0.1.0.dist-info/METADATA
machine_learn-0.1.0.dist-info/WHEEL
machine_learn-0.1.0.dist-info/RECORD
